{
  "id": "3597934",
  "name": "vue-vite",
  "font_family": "iconfont",
  "css_prefix_text": "icon-",
  "description": "",
  "glyphs": [
    {
      "icon_id": "1304886",
      "name": "收起菜单",
      "font_class": "shouqicaidan",
      "unicode": "e622",
      "unicode_decimal": 58914
    },
    {
      "icon_id": "1304894",
      "name": "展开菜单",
      "font_class": "zhankaicaidan",
      "unicode": "e624",
      "unicode_decimal": 58916
    },
    {
      "icon_id": "2791",
      "name": "tanx",
      "font_class": "tanx",
      "unicode": "e600",
      "unicode_decimal": 58880
    },
    {
      "icon_id": "629333",
      "name": "设置",
      "font_class": "shezhi",
      "unicode": "e64b",
      "unicode_decimal": 58955
    },
    {
      "icon_id": "15660242",
      "name": "仪表盘",
      "font_class": "yibiaopan",
      "unicode": "eab4",
      "unicode_decimal": 60084
    }
  ]
}
